Workbook
Name ALIAS: Actuación!$C$8:$C$401
Name ALIAS: #REF!
Name baremo: #REF!
Name BAREMOS: Actuación!$G$8:$G$401
Name BAREMOS: #REF!
Name BORRA: Actuación!#REF!
Name BORRA: #REF!
Name codigo: #REF!
Name CODIGOS: Actuación!$B$8:$B$401
Name CODIGOS: #REF!
Name concepto: #REF!
Name datos: Actuación!#REF!
Name datos: #REF!
Name TIPO: Actuación!$H$8:$H$401
Name TIPO: #REF!

Sheet Actuación
P1: Contrato: | Q1: =MID(F2,8,1)
B2: Provincia: | E2: Contrato: | F2: =IF(F4<Q2,"No válido", IF(F4<Q3,P2, IF(F4<Q4,P3, IF(F4<Q5,P4, IF(F4<Q6,P5, IF(F4<Q7,P6, IF(F4<Q8,P7, IF(F4<T2,P8, IF(F4<T3,S2, IF(F4<T4,S3, IF(F4<T5,S4, IF(F4<T6,S5, IF(F4<T7,S6, IF(F4<T8,S7, IF(F4<W2,S8, IF(F4<W3,V2, IF(F4<W4,V3, IF(F4<W5,V4, IF(F4<W6,V5, IF(F4<W7,V6, IF(F4<W8,V7,V8))))))))))))))))))))) -> 2025A | H2: Contratos Vigentes: | J2: Total LyC | K2: Total Desm. | L2: Total O.C.: | P2: 2025B | Q2: 45658
B3: Proyecto: | E3: Período: | J3: =SUM(J10:J64880) -> 0 | K3: =SUM(K10:K64880) -> 0 | L3: =SUM(L10:L64882) -> 0 | P3: 2023A | Q3: 44440
B4: Titulo: | E4: F. Ejec.: | F4: 45771 | H4: 2023B
B5: Ocra / Act. : | H5: 2025A | J5: Plantilla: | K5: Parte: | L5: Versión:
B6: Título: | J6: COLISEO | K6: Tipo II | L6: 4
K7: Actualizado: | L7: 45658
A8: Asignada a: | D8: TARE | E8: Puntos | G8: Plano/Hoja | I8: NUM. | J8: =SUBTOTAL(9,J10:J401) -> 0 | K8: =SUBTOTAL(9,K10:K401) -> 0 | L8: =SUBTOTAL(9,L10:L401) -> 0 | V8: 2025A | W8: 44440
A9: Brigada (Código) | B9: CODIGO | C9: DESCRIPCION | D9: MATE | E9: Unidades Tarea | F9: BAREMO | G9: PL | H9: HO | I9: EMP | J9: Instalación | K9: Desmontaje | L9: Obra Civil | M9: Contrato según fecha
C10: =IF(B10="","", IF(M10=$H$5,IFERROR(VLOOKUP(B10,'Baremos actuales'!A:E,5,FALSE),"No encontrado. Revisar código, fecha ejecución y/o contrato."), IF(M10=$H$4,IFERROR(VLOOKUP(B10,'Baremos anteriores'!A:E,5,FALSE),"No encontrado. Revisar código, fecha ejecución y/o contrato."), IF(M10=$H$3,IFERROR(VLOOKUP(B10,#REF!,5,FALSE),"No encontrado. Revisar código, fecha ejecución y/o contrato."), IF(D10="","Código no encontrado", IF(D10="ERROR","No encontrado. Revisar Código, fecha de ejecución y/o contrato.", IF(D10="MATE", IF(C9="DESCRIPCION","NO SE PUEDE COMENZAR SIN CÓDIGO DE TAREA", IF(C9="","FALTA CÓDIGO DE TAREA", CONCATENATE(" ",VLOOKUP(B10,'Maestro Materiales'!A:C,3,FALSE)))),IFERROR(VLOOKUP(B10,#REF!,5,FALSE),"No encontrado. Revisar código, fecha ejecución y/o contrato.")))))))) | D10: =IF(B10="","", IFERROR(VLOOKUP(B10,'Maestro Materiales'!A:C,2,FALSE), IFERROR(VLOOKUP(B10,'Baremos actuales'!A:B,2,FALSE), IFERROR(VLOOKUP(B10,'Baremos anteriores'!A:B,2,FALSE), "")))) | F10: =IF(D10="MATE", IF(E10="","¿Unidades?",""), IF(D10="",IF(E10="","","¿Código?"), IF(E10="","¿Unidades?", IF(D10="TARE", IF(M10=$H$3,IFERROR(VLOOKUP(B10,'Baremos actuales'!A:C,3,FALSE),0), IF(M10=$H$4,IFERROR(VLOOKUP(B10,'Baremos anteriores'!A:C,3,FALSE),0),0)))))) | J10: =IF($D10="","", IF($E10="","", IF($D10="MATE","", IF(VLOOKUP($B10,'Baremos actuales'!A:D,4,FALSE)=J$9,$E10*$F10,IF(VLOOKUP($B10,'Baremos anteriores'!A:D,4,FALSE)="Sin Definir",$E10*$F10,""))))) | K10: =IF($D10="","", IF($E10="","", IF($D10="MATE","", IF(VLOOKUP($B10,'Baremos actuales'!$A:$D,4,FALSE)=K$9,$E10*$F10,IF(VLOOKUP($B10,'Baremos anteriores'!$A:$D,4,FALSE)="Desmonte",$E10*$F10,""))))) | L10: =IF($D10="","", IF($E10="","", IF($D10="MATE","", IF(VLOOKUP($B10,'Baremos actuales'!$A:$D,4,FALSE)=L$9,$E10*$F10,"")))) | M10: =IF(D10="MATE","Materiales",IF(B10="","", IF($Q$1="O","Obsoleto",$F$2)))
C11: =IF(B11="","", IF(M11=$H$5,IFERROR(VLOOKUP(B11,'Baremos actuales'!A:E,5,FALSE),"No encontrado. Revisar código, fecha ejecución y/o contrato."), IF(M11=$H$4,IFERROR(VLOOKUP(B11,'Baremos anteriores'!A:E,5,FALSE),"No encontrado. Revisar código, fecha ejecución y/o contrato."), IF(M11=$H$3,IFERROR(VLOOKUP(B11,#REF!,5,FALSE),"No encontrado. Revisar código, fecha ejecución y/o contrato."), IF(D11="","Código no encontrado", IF(D11="ERROR","No encontrado. Revisar Código, fecha de ejecución y/o contrato.", IF(D11="MATE", IF(C10="DESCRIPCION","NO SE PUEDE COMENZAR SIN CÓDIGO DE TAREA", IF(C10="","FALTA CÓDIGO DE TAREA", CONCATENATE(" ",VLOOKUP(B11,'Maestro Materiales'!A:C,3,FALSE)))),IFERROR(VLOOKUP(B11,#REF!,5,FALSE),"No encontrado. Revisar código, fecha ejecución y/o contrato.")))))))) | D11: =IF(B11="","", IFERROR(VLOOKUP(B11,'Maestro Materiales'!A:C,2,FALSE), IFERROR(VLOOKUP(B11,'Baremos actuales'!A:B,2,FALSE), IFERROR(VLOOKUP(B11,'Baremos anteriores'!A:B,2,FALSE), "")))) | F11: =IF(D11="MATE", IF(E11="","¿Unidades?",""), IF(D11="",IF(E11="","","¿Código?"), IF(E11="","¿Unidades?", IF(D11="TARE", IF(M11=$H$3,IFERROR(VLOOKUP(B11,'Baremos actuales'!A:C,3,FALSE),0), IF(M11=$H$4,IFERROR(VLOOKUP(B11,'Baremos anteriores'!A:C,3,FALSE),0),0)))))) | J11: =IF($D11="","", IF($E11="","", IF($D11="MATE","", IF(VLOOKUP($B11,'Baremos actuales'!A:D,4,FALSE)=J$9,$E11*$F11,IF(VLOOKUP($B11,'Baremos anteriores'!A:D,4,FALSE)="Sin Definir",$E11*$F11,""))))) | K11: =IF($D11="","", IF($E11="","", IF($D11="MATE","", IF(VLOOKUP($B11,'Baremos actuales'!$A:$D,4,FALSE)=K$9,$E11*$F11,IF(VLOOKUP($B11,'Baremos anteriores'!$A:$D,4,FALSE)="Desmonte",$E11*$F11,""))))) | L11: =IF($D11="","", IF($E11="","", IF($D11="MATE","", IF(VLOOKUP($B11,'Baremos actuales'!$A:$D,4,FALSE)=L$9,$E11*$F11,"")))) | M11: =IF(D11="MATE","Materiales",IF(B11="","", IF($Q$1="O","Obsoleto",$F$2)))
C12: =IF(B12="","", IF(M12=$H$5,IFERROR(VLOOKUP(B12,'Baremos actuales'!A:E,5,FALSE),"No encontrado. Revisar código, fecha ejecución y/o contrato."), IF(M12=$H$4,IFERROR(VLOOKUP(B12,'Baremos anteriores'!A:E,5,FALSE),"No encontrado. Revisar código, fecha ejecución y/o contrato."), IF(M12=$H$3,IFERROR(VLOOKUP(B12,#REF!,5,FALSE),"No encontrado. Revisar código, fecha ejecución y/o contrato."), IF(D12="","Código no encontrado", IF(D12="ERROR","No encontrado. Revisar Código, fecha de ejecución y/o contrato.", IF(D12="MATE", IF(C11="DESCRIPCION","NO SE PUEDE COMENZAR SIN CÓDIGO DE TAREA", IF(C11="","FALTA CÓDIGO DE TAREA", CONCATENATE(" ",VLOOKUP(B12,'Maestro Materiales'!A:C,3,FALSE)))),IFERROR(VLOOKUP(B12,#REF!,5,FALSE),"No encontrado. Revisar código, fecha ejecución y/o contrato.")))))))) | D12: =IF(B12="","", IFERROR(VLOOKUP(B12,'Maestro Materiales'!A:C,2,FALSE), IFERROR(VLOOKUP(B12,'Baremos actuales'!A:B,2,FALSE), IFERROR(VLOOKUP(B12,'Baremos anteriores'!A:B,2,FALSE), "")))) | F12: =IF(D12="MATE", IF(E12="","¿Unidades?",""), IF(D12="",IF(E12="","","¿Código?"), IF(E12="","¿Unidades?", IF(D12="TARE", IF(M12=$H$3,IFERROR(VLOOKUP(B12,'Baremos actuales'!A:C,3,FALSE),0), IF(M12=$H$4,IFERROR(VLOOKUP(B12,'Baremos anteriores'!A:C,3,FALSE),0),0)))))) | J12: =IF($D12="","", IF($E12="","", IF($D12="MATE","", IF(VLOOKUP($B12,'Baremos actuales'!A:D,4,FALSE)=J$9,$E12*$F12,IF(VLOOKUP($B12,'Baremos anteriores'!A:D,4,FALSE)="Sin Definir",$E12*$F12,""))))) | K12: =IF($D12="","", IF($E12="","", IF($D12="MATE","", IF(VLOOKUP($B12,'Baremos actuales'!$A:$D,4,FALSE)=K$9,$E12*$F12,IF(VLOOKUP($B12,'Baremos anteriores'!$A:$D,4,FALSE)="Desmonte",$E12*$F12,""))))) | L12: =IF($D12="","", IF($E12="","", IF($D12="MATE","", IF(VLOOKUP($B12,'Baremos actuales'!$A:$D,4,FALSE)=L$9,$E12*$F12,"")))) | M12: =IF(D12="MATE","Materiales",IF(B12="","", IF($Q$1="O","Obsoleto",$F$2)))
C13: =IF(B13="","", IF(M13=$H$5,IFERROR(VLOOKUP(B13,'Baremos actuales'!A:E,5,FALSE),"No encontrado. Revisar código, fecha ejecución y/o contrato."), IF(M13=$H$4,IFERROR(VLOOKUP(B13,'Baremos anteriores'!A:E,5,FALSE),"No encontrado. Revisar código, fecha ejecución y/o contrato."), IF(M13=$H$3,IFERROR(VLOOKUP(B13,#REF!,5,FALSE),"No encontrado. Revisar código, fecha ejecución y/o contrato."), IF(D13="","Código no encontrado", IF(D13="ERROR","No encontrado. Revisar Código, fecha de ejecución y/o contrato.", IF(D13="MATE", IF(C12="DESCRIPCION","NO SE PUEDE COMENZAR SIN CÓDIGO DE TAREA", IF(C12="","FALTA CÓDIGO DE TAREA", CONCATENATE(" ",VLOOKUP(B13,'Maestro Materiales'!A:C,3,FALSE)))),IFERROR(VLOOKUP(B13,#REF!,5,FALSE),"No encontrado. Revisar código, fecha ejecución y/o contrato.")))))))) | D13: =IF(B13="","", IFERROR(VLOOKUP(B13,'Maestro Materiales'!A:C,2,FALSE), IFERROR(VLOOKUP(B13,'Baremos actuales'!A:B,2,FALSE), IFERROR(VLOOKUP(B13,'Baremos anteriores'!A:B,2,FALSE), "")))) | F13: =IF(D13="MATE", IF(E13="","¿Unidades?",""), IF(D13="",IF(E13="","","¿Código?"), IF(E13="","¿Unidades?", IF(D13="TARE", IF(M13=$H$3,IFERROR(VLOOKUP(B13,'Baremos actuales'!A:C,3,FALSE),0), IF(M13=$H$4,IFERROR(VLOOKUP(B13,'Baremos anteriores'!A:C,3,FALSE),0),0)))))) | J13: =IF($D13="","", IF($E13="","", IF($D13="MATE","", IF(VLOOKUP($B13,'Baremos actuales'!A:D,4,FALSE)=J$9,$E13*$F13,IF(VLOOKUP($B13,'Baremos anteriores'!A:D,4,FALSE)="Sin Definir",$E13*$F13,""))))) | K13: =IF($D13="","", IF($E13="","", IF($D13="MATE","", IF(VLOOKUP($B13,'Baremos actuales'!$A:$D,4,FALSE)=K$9,$E13*$F13,IF(VLOOKUP($B13,'Baremos anteriores'!$A:$D,4,FALSE)="Desmonte",$E13*$F13,""))))) | L13: =IF($D13="","", IF($E13="","", IF($D13="MATE","", IF(VLOOKUP($B13,'Baremos actuales'!$A:$D,4,FALSE)=L$9,$E13*$F13,"")))) | M13: =IF(D13="MATE","Materiales",IF(B13="","", IF($Q$1="O","Obsoleto",$F$2)))
C14: =IF(B14="","", IF(M14=$H$5,IFERROR(VLOOKUP(B14,'Baremos actuales'!A:E,5,FALSE),"No encontrado. Revisar código, fecha ejecución y/o contrato."), IF(M14=$H$4,IFERROR(VLOOKUP(B14,'Baremos anteriores'!A:E,5,FALSE),"No encontrado. Revisar código, fecha ejecución y/o contrato."), IF(M14=$H$3,IFERROR(VLOOKUP(B14,#REF!,5,FALSE),"No encontrado. Revisar código, fecha ejecución y/o contrato."), IF(D14="","Código no encontrado", IF(D14="ERROR","No encontrado. Revisar Código, fecha de ejecución y/o contrato.", IF(D14="MATE", IF(C13="DESCRIPCION","NO SE PUEDE COMENZAR SIN CÓDIGO DE TAREA", IF(C13="","FALTA CÓDIGO DE TAREA", CONCATENATE(" ",VLOOKUP(B14,'Maestro Materiales'!A:C,3,FALSE)))),IFERROR(VLOOKUP(B14,#REF!,5,FALSE),"No encontrado. Revisar código, fecha ejecución y/o contrato.")))))))) | D14: =IF(B14="","", IFERROR(VLOOKUP(B14,'Maestro Materiales'!A:C,2,FALSE), IFERROR(VLOOKUP(B14,'Baremos actuales'!A:B,2,FALSE), IFERROR(VLOOKUP(B14,'Baremos anteriores'!A:B,2,FALSE), "")))) | F14: =IF(D14="MATE", IF(E14="","¿Unidades?",""), IF(D14="",IF(E14="","","¿Código?"), IF(E14="","¿Unidades?", IF(D14="TARE", IF(M14=$H$3,IFERROR(VLOOKUP(B14,'Baremos actuales'!A:C,3,FALSE),0), IF(M14=$H$4,IFERROR(VLOOKUP(B14,'Baremos anteriores'!A:C,3,FALSE),0),0)))))) | J14: =IF($D14="","", IF($E14="","", IF($D14="MATE","", IF(VLOOKUP($B14,'Baremos actuales'!A:D,4,FALSE)=J$9,$E14*$F14,IF(VLOOKUP($B14,'Baremos anteriores'!A:D,4,FALSE)="Sin Definir",$E14*$F14,""))))) | K14: =IF($D14="","", IF($E14="","", IF($D14="MATE","", IF(VLOOKUP($B14,'Baremos actuales'!$A:$D,4,FALSE)=K$9,$E14*$F14,IF(VLOOKUP($B14,'Baremos anteriores'!$A:$D,4,FALSE)="Desmonte",$E14*$F14,""))))) | L14: =IF($D14="","", IF($E14="","", IF($D14="MATE","", IF(VLOOKUP($B14,'Baremos actuales'!$A:$D,4,FALSE)=L$9,$E14*$F14,"")))) | M14: =IF(D14="MATE","Materiales",IF(B14="","", IF($Q$1="O","Obsoleto",$F$2)))
C15: =IF(B15="","", IF(M15=$H$5,IFERROR(VLOOKUP(B15,'Baremos actuales'!A:E,5,FALSE),"No encontrado. Revisar código, fecha ejecución y/o contrato."), IF(M15=$H$4,IFERROR(VLOOKUP(B15,'Baremos anteriores'!A:E,5,FALSE),"No encontrado. Revisar código, fecha ejecución y/o contrato."), IF(M15=$H$3,IFERROR(VLOOKUP(B15,#REF!,5,FALSE),"No encontrado. Revisar código, fecha ejecución y/o contrato."), IF(D15="","Código no encontrado", IF(D15="ERROR","No encontrado. Revisar Código, fecha de ejecución y/o contrato.", IF(D15="MATE", IF(C14="DESCRIPCION","NO SE PUEDE COMENZAR SIN CÓDIGO DE TAREA", IF(C14="","FALTA CÓDIGO DE TAREA", CONCATENATE(" ",VLOOKUP(B15,'Maestro Materiales'!A:C,3,FALSE)))),IFERROR(VLOOKUP(B15,#REF!,5,FALSE),"No encontrado. Revisar código, fecha ejecución y/o contrato.")))))))) | D15: =IF(B15="","", IFERROR(VLOOKUP(B15,'Maestro Materiales'!A:C,2,FALSE), IFERROR(VLOOKUP(B15,'Baremos actuales'!A:B,2,FALSE), IFERROR(VLOOKUP(B15,'Baremos anteriores'!A:B,2,FALSE), "")))) | F15: =IF(D15="MATE", IF(E15="","¿Unidades?",""), IF(D15="",IF(E15="","","¿Código?"), IF(E15="","¿Unidades?", IF(D15="TARE", IF(M15=$H$3,IFERROR(VLOOKUP(B15,'Baremos actuales'!A:C,3,FALSE),0), IF(M15=$H$4,IFERROR(VLOOKUP(B15,'Baremos anteriores'!A:C,3,FALSE),0),0)))))) | J15: =IF($D15="","", IF($E15="","", IF($D15="MATE","", IF(VLOOKUP($B15,'Baremos actuales'!A:D,4,FALSE)=J$9,$E15*$F15,IF(VLOOKUP($B15,'Baremos anteriores'!A:D,4,FALSE)="Sin Definir",$E15*$F15,""))))) | K15: =IF($D15="","", IF($E15="","", IF($D15="MATE","", IF(VLOOKUP($B15,'Baremos actuales'!$A:$D,4,FALSE)=K$9,$E15*$F15,IF(VLOOKUP($B15,'Baremos anteriores'!$A:$D,4,FALSE)="Desmonte",$E15*$F15,""))))) | L15: =IF($D15="","", IF($E15="","", IF($D15="MATE","", IF(VLOOKUP($B15,'Baremos actuales'!$A:$D,4,FALSE)=L$9,$E15*$F15,"")))) | M15: =IF(D15="MATE","Materiales",IF(B15="","", IF($Q$1="O","Obsoleto",$F$2)))
C16: =IF(B16="","", IF(M16=$H$5,IFERROR(VLOOKUP(B16,'Baremos actuales'!A:E,5,FALSE),"No encontrado. Revisar código, fecha ejecución y/o contrato."), IF(M16=$H$4,IFERROR(VLOOKUP(B16,'Baremos anteriores'!A:E,5,FALSE),"No encontrado. Revisar código, fecha ejecución y/o contrato."), IF(M16=$H$3,IFERROR(VLOOKUP(B16,#REF!,5,FALSE),"No encontrado. Revisar código, fecha ejecución y/o contrato."), IF(D16="","Código no encontrado", IF(D16="ERROR","No encontrado. Revisar Código, fecha de ejecución y/o contrato.", IF(D16="MATE", IF(C15="DESCRIPCION","NO SE PUEDE COMENZAR SIN CÓDIGO DE TAREA", IF(C15="","FALTA CÓDIGO DE TAREA", CONCATENATE(" ",VLOOKUP(B16,'Maestro Materiales'!A:C,3,FALSE)))),IFERROR(VLOOKUP(B16,#REF!,5,FALSE),"No encontrado. Revisar código, fecha ejecución y/o contrato.")))))))) | D16: =IF(B16="","", IFERROR(VLOOKUP(B16,'Maestro Materiales'!A:C,2,FALSE), IFERROR(VLOOKUP(B16,'Baremos actuales'!A:B,2,FALSE), IFERROR(VLOOKUP(B16,'Baremos anteriores'!A:B,2,FALSE), "")))) | F16: =IF(D16="MATE", IF(E16="","¿Unidades?",""), IF(D16="",IF(E16="","","¿Código?"), IF(E16="","¿Unidades?", IF(D16="TARE", IF(M16=$H$3,IFERROR(VLOOKUP(B16,'Baremos actuales'!A:C,3,FALSE),0), IF(M16=$H$4,IFERROR(VLOOKUP(B16,'Baremos anteriores'!A:C,3,FALSE),0),0)))))) | J16: =IF($D16="","", IF($E16="","", IF($D16="MATE","", IF(VLOOKUP($B16,'Baremos actuales'!A:D,4,FALSE)=J$9,$E16*$F16,IF(VLOOKUP($B16,'Baremos anteriores'!A:D,4,FALSE)="Sin Definir",$E16*$F16,""))))) | K16: =IF($D16="","", IF($E16="","", IF($D16="MATE","", IF(VLOOKUP($B16,'Baremos actuales'!$A:$D,4,FALSE)=K$9,$E16*$F16,IF(VLOOKUP($B16,'Baremos anteriores'!$A:$D,4,FALSE)="Desmonte",$E16*$F16,""))))) | L16: =IF($D16="","", IF($E16="","", IF($D16="MATE","", IF(VLOOKUP($B16,'Baremos actuales'!$A:$D,4,FALSE)=L$9,$E16*$F16,"")))) | M16: =IF(D16="MATE","Materiales",IF(B16="","", IF($Q$1="O","Obsoleto",$F$2)))
C17: =IF(B17="","", IF(M17=$H$5,IFERROR(VLOOKUP(B17,'Baremos actuales'!A:E,5,FALSE),"No encontrado. Revisar código, fecha ejecución y/o contrato."), IF(M17=$H$4,IFERROR(VLOOKUP(B17,'Baremos anteriores'!A:E,5,FALSE),"No encontrado. Revisar código, fecha ejecución y/o contrato."), IF(M17=$H$3,IFERROR(VLOOKUP(B17,#REF!,5,FALSE),"No encontrado. Revisar código, fecha ejecución y/o contrato."), IF(D17="","Código no encontrado", IF(D17="ERROR","No encontrado. Revisar Código, fecha de ejecución y/o contrato.", IF(D17="MATE", IF(C16="DESCRIPCION","NO SE PUEDE COMENZAR SIN CÓDIGO DE TAREA", IF(C16="","FALTA CÓDIGO DE TAREA", CONCATENATE(" ",VLOOKUP(B17,'Maestro Materiales'!A:C,3,FALSE)))),IFERROR(VLOOKUP(B17,#REF!,5,FALSE),"No encontrado. Revisar código, fecha ejecución y/o contrato.")))))))) | D17: =IF(B17="","", IFERROR(VLOOKUP(B17,'Maestro Materiales'!A:C,2,FALSE), IFERROR(VLOOKUP(B17,'Baremos actuales'!A:B,2,FALSE), IFERROR(VLOOKUP(B17,'Baremos anteriores'!A:B,2,FALSE), "")))) | F17: =IF(D17="MATE", IF(E17="","¿Unidades?",""), IF(D17="",IF(E17="","","¿Código?"), IF(E17="","¿Unidades?", IF(D17="TARE", IF(M17=$H$3,IFERROR(VLOOKUP(B17,'Baremos actuales'!A:C,3,FALSE),0), IF(M17=$H$4,IFERROR(VLOOKUP(B17,'Baremos anteriores'!A:C,3,FALSE),0),0)))))) | J17: =IF($D17="","", IF($E17="","", IF($D17="MATE","", IF(VLOOKUP($B17,'Baremos actuales'!A:D,4,FALSE)=J$9,$E17*$F17,IF(VLOOKUP($B17,'Baremos anteriores'!A:D,4,FALSE)="Sin Definir",$E17*$F17,""))))) | K17: =IF($D17="","", IF($E17="","", IF($D17="MATE","", IF(VLOOKUP($B17,'Baremos actuales'!$A:$D,4,FALSE)=K$9,$E17*$F17,IF(VLOOKUP($B17,'Baremos anteriores'!$A:$D,4,FALSE)="Desmonte",$E17*$F17,""))))) | L17: =IF($D17="","", IF($E17="","", IF($D17="MATE","", IF(VLOOKUP($B17,'Baremos actuales'!$A:$D,4,FALSE)=L$9,$E17*$F17,"")))) | M17: =IF(D17="MATE","Materiales",IF(B17="","", IF($Q$1="O","Obsoleto",$F$2)))
C18: =IF(B18="","", IF(M18=$H$5,IFERROR(VLOOKUP(B18,'Baremos actuales'!A:E,5,FALSE),"No encontrado. Revisar código, fecha ejecución y/o contrato."), IF(M18=$H$4,IFERROR(VLOOKUP(B18,'Baremos anteriores'!A:E,5,FALSE),"No encontrado. Revisar código, fecha ejecución y/o contrato."), IF(M18=$H$3,IFERROR(VLOOKUP(B18,#REF!,5,FALSE),"No encontrado. Revisar código, fecha ejecución y/o contrato."), IF(D18="","Código no encontrado", IF(D18="ERROR","No encontrado. Revisar Código, fecha de ejecución y/o contrato.", IF(D18="MATE", IF(C17="DESCRIPCION","NO SE PUEDE COMENZAR SIN CÓDIGO DE TAREA", IF(C17="","FALTA CÓDIGO DE TAREA", CONCATENATE(" ",VLOOKUP(B18,'Maestro Materiales'!A:C,3,FALSE)))),IFERROR(VLOOKUP(B18,#REF!,5,FALSE),"No encontrado. Revisar código, fecha ejecución y/o contrato.")))))))) | D18: =IF(B18="","", IFERROR(VLOOKUP(B18,'Maestro Materiales'!A:C,2,FALSE), IFERROR(VLOOKUP(B18,'Baremos actuales'!A:B,2,FALSE), IFERROR(VLOOKUP(B18,'Baremos anteriores'!A:B,2,FALSE), "")))) | F18: =IF(D18="MATE", IF(E18="","¿Unidades?",""), IF(D18="",IF(E18="","","¿Código?"), IF(E18="","¿Unidades?", IF(D18="TARE", IF(M18=$H$3,IFERROR(VLOOKUP(B18,'Baremos actuales'!A:C,3,FALSE),0), IF(M18=$H$4,IFERROR(VLOOKUP(B18,'Baremos anteriores'!A:C,3,FALSE),0),0)))))) | J18: =IF($D18="","", IF($E18="","", IF($D18="MATE","", IF(VLOOKUP($B18,'Baremos actuales'!A:D,4,FALSE)=J$9,$E18*$F18,IF(VLOOKUP($B18,'Baremos anteriores'!A:D,4,FALSE)="Sin Definir",$E18*$F18,""))))) | K18: =IF($D18="","", IF($E18="","", IF($D18="MATE","", IF(VLOOKUP($B18,'Baremos actuales'!$A:$D,4,FALSE)=K$9,$E18*$F18,IF(VLOOKUP($B18,'Baremos anteriores'!$A:$D,4,FALSE)="Desmonte",$E18*$F18,""))))) | L18: =IF($D18="","", IF($E18="","", IF($D18="MATE","", IF(VLOOKUP($B18,'Baremos actuales'!$A:$D,4,FALSE)=L$9,$E18*$F18,"")))) | M18: =IF(D18="MATE","Materiales",IF(B18="","", IF($Q$1="O","Obsoleto",$F$2)))
C19: =IF(B19="","", IF(M19=$H$5,IFERROR(VLOOKUP(B19,'Baremos actuales'!A:E,5,FALSE),"No encontrado. Revisar código, fecha ejecución y/o contrato."), IF(M19=$H$4,IFERROR(VLOOKUP(B19,'Baremos anteriores'!A:E,5,FALSE),"No encontrado. Revisar código, fecha ejecución y/o contrato."), IF(M19=$H$3,IFERROR(VLOOKUP(B19,#REF!,5,FALSE),"No encontrado. Revisar código, fecha ejecución y/o contrato."), IF(D19="","Código no encontrado", IF(D19="ERROR","No encontrado. Revisar Código, fecha de ejecución y/o contrato.", IF(D19="MATE", IF(C18="DESCRIPCION","NO SE PUEDE COMENZAR SIN CÓDIGO DE TAREA", IF(C18="","FALTA CÓDIGO DE TAREA", CONCATENATE(" ",VLOOKUP(B19,'Maestro Materiales'!A:C,3,FALSE)))),IFERROR(VLOOKUP(B19,#REF!,5,FALSE),"No encontrado. Revisar código, fecha ejecución y/o contrato.")))))))) | D19: =IF(B19="","", IFERROR(VLOOKUP(B19,'Maestro Materiales'!A:C,2,FALSE), IFERROR(VLOOKUP(B19,'Baremos actuales'!A:B,2,FALSE), IFERROR(VLOOKUP(B19,'Baremos anteriores'!A:B,2,FALSE), "")))) | F19: =IF(D19="MATE", IF(E19="","¿Unidades?",""), IF(D19="",IF(E19="","","¿Código?"), IF(E19="","¿Unidades?", IF(D19="TARE", IF(M19=$H$3,IFERROR(VLOOKUP(B19,'Baremos actuales'!A:C,3,FALSE),0), IF(M19=$H$4,IFERROR(VLOOKUP(B19,'Baremos anteriores'!A:C,3,FALSE),0),0)))))) | J19: =IF($D19="","", IF($E19="","", IF($D19="MATE","", IF(VLOOKUP($B19,'Baremos actuales'!A:D,4,FALSE)=J$9,$E19*$F19,IF(VLOOKUP($B19,'Baremos anteriores'!A:D,4,FALSE)="Sin Definir",$E19*$F19,""))))) | K19: =IF($D19="","", IF($E19="","", IF($D19="MATE","", IF(VLOOKUP($B19,'Baremos actuales'!$A:$D,4,FALSE)=K$9,$E19*$F19,IF(VLOOKUP($B19,'Baremos anteriores'!$A:$D,4,FALSE)="Desmonte",$E19*$F19,""))))) | L19: =IF($D19="","", IF($E19="","", IF($D19="MATE","", IF(VLOOKUP($B19,'Baremos actuales'!$A:$D,4,FALSE)=L$9,$E19*$F19,"")))) | M19: =IF(D19="MATE","Materiales",IF(B19="","", IF($Q$1="O","Obsoleto",$F$2)))
C20: =IF(B20="","", IF(M20=$H$5,IFERROR(VLOOKUP(B20,'Baremos actuales'!A:E,5,FALSE),"No encontrado. Revisar código, fecha ejecución y/o contrato."), IF(M20=$H$4,IFERROR(VLOOKUP(B20,'Baremos anteriores'!A:E,5,FALSE),"No encontrado. Revisar código, fecha ejecución y/o contrato."), IF(M20=$H$3,IFERROR(VLOOKUP(B20,#REF!,5,FALSE),"No encontrado. Revisar código, fecha ejecución y/o contrato."), IF(D20="","Código no encontrado", IF(D20="ERROR","No encontrado. Revisar Código, fecha de ejecución y/o contrato.", IF(D20="MATE", IF(C19="DESCRIPCION","NO SE PUEDE COMENZAR SIN CÓDIGO DE TAREA", IF(C19="","FALTA CÓDIGO DE TAREA", CONCATENATE(" ",VLOOKUP(B20,'Maestro Materiales'!A:C,3,FALSE)))),IFERROR(VLOOKUP(B20,#REF!,5,FALSE),"No encontrado. Revisar código, fecha ejecución y/o contrato.")))))))) | D20: =IF(B20="","", IFERROR(VLOOKUP(B20,'Maestro Materiales'!A:C,2,FALSE), IFERROR(VLOOKUP(B20,'Baremos actuales'!A:B,2,FALSE), IFERROR(VLOOKUP(B20,'Baremos anteriores'!A:B,2,FALSE), "")))) | F20: =IF(D20="MATE", IF(E20="","¿Unidades?",""), IF(D20="",IF(E20="","","¿Código?"), IF(E20="","¿Unidades?", IF(D20="TARE", IF(M20=$H$3,IFERROR(VLOOKUP(B20,'Baremos actuales'!A:C,3,FALSE),0), IF(M20=$H$4,IFERROR(VLOOKUP(B20,'Baremos anteriores'!A:C,3,FALSE),0),0)))))) | J20: =IF($D20="","", IF($E20="","", IF($D20="MATE","", IF(VLOOKUP($B20,'Baremos actuales'!A:D,4,FALSE)=J$9,$E20*$F20,IF(VLOOKUP($B20,'Baremos anteriores'!A:D,4,FALSE)="Sin Definir",$E20*$F20,""))))) | K20: =IF($D20="","", IF($E20="","", IF($D20="MATE","", IF(VLOOKUP($B20,'Baremos actuales'!$A:$D,4,FALSE)=K$9,$E20*$F20,IF(VLOOKUP($B20,'Baremos anteriores'!$A:$D,4,FALSE)="Desmonte",$E20*$F20,""))))) | L20: =IF($D20="","", IF($E20="","", IF($D20="MATE","", IF(VLOOKUP($B20,'Baremos actuales'!$A:$D,4,FALSE)=L$9,$E20*$F20,"")))) | M20: =IF(D20="MATE","Materiales",IF(B20="","", IF($Q$1="O","Obsoleto",$F$2)))
C21: =IF(B21="","", IF(M21=$H$5,IFERROR(VLOOKUP(B21,'Baremos actuales'!A:E,5,FALSE),"No encontrado. Revisar código, fecha ejecución y/o contrato."), IF(M21=$H$4,IFERROR(VLOOKUP(B21,'Baremos anteriores'!A:E,5,FALSE),"No encontrado. Revisar código, fecha ejecución y/o contrato."), IF(M21=$H$3,IFERROR(VLOOKUP(B21,#REF!,5,FALSE),"No encontrado. Revisar código, fecha ejecución y/o contrato."), IF(D21="","Código no encontrado", IF(D21="ERROR","No encontrado. Revisar Código, fecha de ejecución y/o contrato.", IF(D21="MATE", IF(C20="DESCRIPCION","NO SE PUEDE COMENZAR SIN CÓDIGO DE TAREA", IF(C20="","FALTA CÓDIGO DE TAREA", CONCATENATE(" ",VLOOKUP(B21,'Maestro Materiales'!A:C,3,FALSE)))),IFERROR(VLOOKUP(B21,#REF!,5,FALSE),"No encontrado. Revisar código, fecha ejecución y/o contrato.")))))))) | D21: =IF(B21="","", IFERROR(VLOOKUP(B21,'Maestro Materiales'!A:C,2,FALSE), IFERROR(VLOOKUP(B21,'Baremos actuales'!A:B,2,FALSE), IFERROR(VLOOKUP(B21,'Baremos anteriores'!A:B,2,FALSE), "")))) | F21: =IF(D21="MATE", IF(E21="","¿Unidades?",""), IF(D21="",IF(E21="","","¿Código?"), IF(E21="","¿Unidades?", IF(D21="TARE", IF(M21=$H$3,IFERROR(VLOOKUP(B21,'Baremos actuales'!A:C,3,FALSE),0), IF(M21=$H$4,IFERROR(VLOOKUP(B21,'Baremos anteriores'!A:C,3,FALSE),0),0)))))) | J21: =IF($D21="","", IF($E21="","", IF($D21="MATE","", IF(VLOOKUP($B21,'Baremos actuales'!A:D,4,FALSE)=J$9,$E21*$F21,IF(VLOOKUP($B21,'Baremos anteriores'!A:D,4,FALSE)="Sin Definir",$E21*$F21,""))))) | K21: =IF($D21="","", IF($E21="","", IF($D21="MATE","", IF(VLOOKUP($B21,'Baremos actuales'!$A:$D,4,FALSE)=K$9,$E21*$F21,IF(VLOOKUP($B21,'Baremos anteriores'!$A:$D,4,FALSE)="Desmonte",$E21*$F21,""))))) | L21: =IF($D21="","", IF($E21="","", IF($D21="MATE","", IF(VLOOKUP($B21,'Baremos actuales'!$A:$D,4,FALSE)=L$9,$E21*$F21,"")))) | M21: =IF(D21="MATE","Materiales",IF(B21="","", IF($Q$1="O","Obsoleto",$F$2)))
... C1010: =IF(B1010="","", IF(M1010=$H$5,IFERROR(VLOOKUP(B1010,'Baremos actuales'!A:E,5,FALSE),"No encontrado. Revisar código, fecha ejecución y/o contrato."), IF(M1010=$H$4,IFERROR(VLOOKUP(B1010,'Baremos anteriores'!A:E,5,FALSE),"No encontrado. Revisar código, fecha ejecución y/o contrato."), IF(M1010=$H$3,IFERROR(VLOOKUP(B1010,#REF!,5,FALSE),"No encontrado. Revisar código, fecha ejecución y/o contrato."), IF(D1010="","Código no encontrado", IF(D1010="ERROR","No encontrado. Revisar Código, fecha de ejecución y/o contrato.", IF(D1010="MATE", IF(C1009="DESCRIPCION","NO SE PUEDE COMENZAR SIN CÓDIGO DE TAREA", IF(C1009="","FALTA CÓDIGO DE TAREA", CONCATENATE(" ",VLOOKUP(B1010,'Maestro Materiales'!A:C,3,FALSE)))),IFERROR(VLOOKUP(B1010,#REF!,5,FALSE),"No encontrado. Revisar código, fecha ejecución y/o contrato.")))))))) | D1010: =IF(B1010="","", IFERROR(VLOOKUP(B1010,'Maestro Materiales'!A:C,2,FALSE), IFERROR(VLOOKUP(B1010,'Baremos actuales'!A:B,2,FALSE), IFERROR(VLOOKUP(B1010,'Baremos anteriores'!A:B,2,FALSE), "")))) | F1010: =IF(D1010="MATE", IF(E1010="","¿Unidades?",""), IF(D1010="",IF(E1010="","","¿Código?"), IF(E1010="","¿Unidades?", IF(D1010="TARE", IF(M1010=$H$3,IFERROR(VLOOKUP(B1010,'Baremos actuales'!A:C,3,FALSE),0), IF(M1010=$H$4,IFERROR(VLOOKUP(B1010,'Baremos anteriores'!A:C,3,FALSE),0),0)))))) | J1010: =IF($D1010="","", IF($E1010="","", IF($D1010="MATE","", IF(VLOOKUP($B1010,'Baremos actuales'!A:D,4,FALSE)=J$9,$E1010*$F1010,IF(VLOOKUP($B1010,'Baremos anteriores'!A:D,4,FALSE)="Sin Definir",$E1010*$F1010,""))))) | K1010: =IF($D1010="","", IF($E1010="","", IF($D1010="MATE","", IF(VLOOKUP($B1010,'Baremos actuales'!$A:$D,4,FALSE)=K$9,$E1010*$F1010,IF(VLOOKUP($B1010,'Baremos anteriores'!$A:$D,4,FALSE)="Desmonte",$E1010*$F1010,""))))) | L1010: =IF($D1010="","", IF($E1010="","", IF($D1010="MATE","", IF(VLOOKUP($B1010,'Baremos actuales'!$A:$D,4,FALSE)=L$9,$E1010*$F1010,"")))) | M1010: =IF(D1010="MATE","Materiales",IF(B1010="","", IF($Q$1="O","Obsoleto",$F$2)))

Sheet Maestro Materiales
A1: Código | B1: MATE/TARE | C1: Descripción | D1: VERIF
A2: 22616 | B2: MATE | C2: CONF "B" EQ PARTNER DEMOS. | D2: COLISEO
A3: 30201 | B3: MATE | C3: *poste a-11m (solo desmon) | D3: COLISEO
A4: 30228 | B4: MATE | C4: *poste b-11m (solo desmon) | D4: COLISEO
A5: 30236 | B5: MATE | C5: *poste b-12m (solo desmon) | D5: COLISEO
A6: 30261 | B6: MATE | C6: *poste c-11m (solo desmon) | D6: COLISEO
A7: 30279 | B7: MATE | C7: *poste c-12m (solo desmon) | D7: COLISEO
A8: 30295 | B8: MATE | C8: *poste d-11m (solo desmon) | D8: COLISEO
A9: 30457 | B9: MATE | C9: Cab.plomo 3600p/32 | D9: COLISEO
A10: 30465 | B10: MATE | C10: Cab.plomo 25p/40 | D10: COLISEO
A11: 30481 | B11: MATE | C11: Cab.plomo 100p/40 | D11: COLISEO
A12: 30503 | B12: MATE | C12: Cab.plomo 200p/40 | D12: COLISEO
A13: 30511 | B13: MATE | C13: Cab.plomo 300p/40 | D13: COLISEO
... A862: 99991996 | B862: MATE | C862: POSTE DESMONTADO | D862: COLISEO

Sheet Baremos anteriores
A1: Código | B1: TARE | C1: Baremo | D1: Naturaleza | E1: Descripción | F1: Contrato
A2: 16501 | B2: TARE | C2: 0 | D2: Permisos | E2: Ud.sing.de permisos | F2: 2021B
A3: 165018 | B3: TARE | C3: 0 | D3: Permisos | E3: Concesion de permiso particular cobre | F3: 2021B
A4: 165026 | B4: TARE | C4: 0 | D4: Permisos | E4: Supl.permiso.part.proy/act indep.compl. | F4: 2021B
A5: 165034 | B5: TARE | C5: 0 | D5: Permisos | E5: Peticion de permiso oficial | F5: 2021B
A6: 165042 | B6: TARE | C6: 0 | D6: Permisos | E6: Concesion de permiso oficial | F6: 2021B
A7: 165051 | B7: TARE | C7: 0 | D7: Permisos | E7: Supl.conseg porcent p.partic(d proyecto) | F7: 2021B
A8: 165069 | B8: TARE | C8: 0 | D8: Permisos | E8: Concesion de permiso particular ftth | F8: 2021B
A9: 165077 | B9: TARE | C9: 0 | D9: Permisos | E9: Supl. consec. todos perm. partic (ftth) | F9: 2021B
A10: 165085 | B10: TARE | C10: 0 | D10: Permisos | E10: Petición permiso oficial (Telematico) | F10: 2021B
A11: 165093 | B11: TARE | C11: 0 | D11: Permisos | E11: Concesión permiso oficial (Telematico) | F11: 2021B
A12: 165107 | B12: TARE | C12: 0 | D12: Permisos | E12: Informe especial solicitud permiso oficial | F12: 2021B
A13: 166006 | B13: TARE | C13: 0 | D13: Permisos | E13: Buzoneo en zona de desp. ftth o similar | F13: 2021B
... A500: 999995 | B500: TARE | C500: 0 | D500: Obra Civil | E500: Rep. Manual | F500: 2021B
C501: 0

Sheet Baremos actuales
A1: Código | B1: TARE | C1: Baremo | D1: Naturaleza | E1: Descripción | F1: Contrato
A2: 940054 | B2: TARE | C2: 0 | D2: Sin definir | E2: Unidad singular de c.r. para canal. | F2: 2025B
A3: 930016 | B3: TARE | C3: 0 | D3: Sin definir | E3: Unidad singular de canalizacion | F3: 2025B
A4: 921017 | B4: TARE | C4: 0 | D4: Sin definir | E4: Zanja con Tritubo Enterrado | F4: 2025B
A5: 921009 | B5: TARE | C5: 0 | D5: Sin definir | E5: Instalación de Poste | F5: 2025B
A6: 920096 | B6: TARE | C6: 0 | D6: Sin definir | E6: Circuito sin tendido | F6: 2025B
A7: 911241 | B7: TARE | C7: 0 | D7: Instalación | E7: Uso de medios auxiliares para trabajos en altura en PEX | F7: 2025B
A8: 911232 | B8: TARE | C8: 0 | D8: Instalación | E8: Revisión infraestructura canalizada para servicio Marco | F8: 2025B
A9: 911224 | B9: TARE | C9: 0 | D9: Instalación | E9: Pago por Planta PEX mano de obra | F9: 2025B
A10: 911216 | B10: TARE | C10: 0 | D10: Instalación | E10: Descuento franquicia TLC del PXP | F10: 2025B
A11: 911186 | B11: TARE | C11: 0 | D11: Instalación | E11: Instalacion dispositivo avifauna | F11: 2025B
A12: 911119 | B12: TARE | C12: 0 | D12: Instalación | E12: Transp.camión-grua alamacen emergencia | F12: 2025B
A13: 910236 | B13: TARE | C13: 0 | D13: Instalación | E13: Actualiz reg. de infraest de arq planex | F13: 2025B
... A420: 16004 | B420: TARE | C420: 0 | D420: EETT y Diseño | E420: Ud.sing.de dise¤o | F420: 2025B
